polyexpkde/__init__.py
polyexpkde/ksum.py
polyexpkde/polyexp_kde.py
polyexpkde-0.1.2.dist-info/LICENSE
polyexpkde-0.1.2.dist-info/METADATA
polyexpkde-0.1.2.dist-info/WHEEL
polyexpkde-0.1.2.dist-info/top_level.txt
polyexpkde-0.1.2.dist-info/zip-safe
polyexpkde-0.1.2.dist-info/RECORD
