Metadata-Version: 2.1
Name: polyexpkde
Version: 0.1.2
Summary: Fast KDE with polynomial-exponential kernel
Home-page: http://github.com/calvinmccarter/polyexpkde
Author: Calvin McCarter
Author-email: mccarter.calvin@gmail.com
Maintainer: Calvin McCarter
Maintainer-email: mccarter.calvin@gmail.com
Keywords: KDE,kernel density estimation
Classifier: Development Status :: 3 - Alpha
Classifier: Intended Audience :: Science/Research
Classifier: Intended Audience :: Developers
Classifier: License :: OSI Approved
Classifier: Programming Language :: C
Classifier: Programming Language :: Python
Classifier: Topic :: Software Development
Classifier: Topic :: Scientific/Engineering
Classifier: Operating System :: Microsoft :: Windows
Classifier: Operating System :: POSIX
Classifier: Operating System :: Unix
Classifier: Operating System :: MacOS
Classifier: Programming Language :: Python :: 3.6
Classifier: Programming Language :: Python :: 3.7
Classifier: Programming Language :: Python :: 3.8
License-File: LICENSE
Requires-Dist: numba >=0.48
Requires-Dist: numpy
Requires-Dist: scikit-learn >=0.23
Requires-Dist: scipy >=1.0
